tkwikipage/__init__.py
tkwikipage/tkwikipage.py
tkwikipage-2.0.dist-info/METADATA
tkwikipage-2.0.dist-info/WHEEL
tkwikipage-2.0.dist-info/top_level.txt
tkwikipage-2.0.dist-info/RECORD
