Metadata-Version: 2.1
Name: tkwikipage
Version: 2.0
Summary: Using TkWikiPage tool to generate MD file and publish to Gitlab wiki page
Home-page: https://git.teko.vn/data/libs/wiki-page/
Author: Tuandv
Author-email: tuan.dv@teko.vn
License: UNKNOWN
Platform: UNKNOWN
Classifier: Programming Language :: Python :: 3
Classifier: License :: OSI Approved :: MIT License
Classifier: Operating System :: OS Independent
Requires-Dist: python-gitlab
